{
    "__comment": "Made with TheDestruc7i0n's advancements generator: https://advancements.thedestruc7i0n.ca",
    "display": {
        "title": {
            "text": "I FEEL DAH POWAH"
        },
        "description": {
            "text": "Get a Powered Module"
        },
        "icon": {
            "item": "lunas-mod:powered_module"
        },
        "frame": "challenge",
        "show_toast": true,
        "announce_to_chat": true,
        "hidden": false,
        "background": "minecraft:textures/gui/advancements/backgrounds/stone.png"
    },
    "criteria": {
        "blast": {
            "trigger": "minecraft:inventory_changed",
            "conditions": {
                "items": [
                    {
                        "items": ["lunas-mod:powered_module"],
                        "count": {
                            "min": 1,
                            "max": 64
                        }
                    }
                ]
            }
        }
    },
    "parent": "adventure:module_get",
    "requirements": [
        [
            "blast"
        ]
    ]

}